MANIFEST.in
resource_demo.xml
resource_view.xml
setup.py
./__init__.py
./__openerp__.py
./resource.py
./faces/__init__.py
./faces/observer.py
./faces/pcalendar.py
./faces/plocale.py
./faces/resource.py
./faces/task.py
./faces/timescale.py
./faces/utils.py
i18n/ar.po
i18n/bg.po
i18n/bs.po
i18n/ca.po
i18n/cs.po
i18n/da.po
i18n/de.po
i18n/es.po
i18n/es_CR.po
i18n/es_EC.po
i18n/es_MX.po
i18n/es_VE.po
i18n/et.po
i18n/fi.po
i18n/fr.po
i18n/gl.po
i18n/he.po
i18n/hr.po
i18n/hu.po
i18n/it.po
i18n/ja.po
i18n/lt.po
i18n/mk.po
i18n/mn.po
i18n/nl.po
i18n/pl.po
i18n/pt.po
i18n/pt_BR.po
i18n/resource.pot
i18n/ro.po
i18n/ru.po
i18n/sl.po
i18n/sv.po
i18n/tr.po
i18n/vi.po
i18n/zh_CN.po
images/resource_leaves_calendar.jpeg
images/resource_leaves_form.jpeg
openerp_resource.egg-info/PKG-INFO
openerp_resource.egg-info/SOURCES.txt
openerp_resource.egg-info/dependency_links.txt
openerp_resource.egg-info/requires.txt
openerp_resource.egg-info/top_level.txt
security/ir.model.access.csv
test/duplicate_resource.yml
test/resource.yml